password_lib/__init__.py
password_lib/utils.py
password_lib-0.0.3.dist-info/License
password_lib-0.0.3.dist-info/METADATA
password_lib-0.0.3.dist-info/WHEEL
password_lib-0.0.3.dist-info/top_level.txt
password_lib-0.0.3.dist-info/RECORD
