Metadata-Version: 2.1
Name: password_lib
Version: 0.0.3
Summary:  `password-lib` is a Python library for generating secure passwords, configuring strength requirements, and checking password strength. With customizable length and requirements, it enhances application security. Use password-lib to easily generate strong passwords and ensure password security.
Author-email: Ahamed Ruyefa <ruyefadf@gmail.com>
Project-URL: Homepage, https://github.com/ardf/password_utils
Project-URL: Bug Tracker, https://github.com/ardf/password_utils/issues
Classifier: Programming Language :: Python :: 3
Classifier: License :: OSI Approved :: MIT License
Classifier: Operating System :: OS Independent
Requires-Python: >=3.9
License-File: License
